odoo/addons/contract_price_revision/README.rst
odoo/addons/contract_price_revision/__init__.py
odoo/addons/contract_price_revision/__manifest__.py
odoo/addons/contract_price_revision/i18n/ca.po
odoo/addons/contract_price_revision/i18n/contract_price_revision.pot
odoo/addons/contract_price_revision/i18n/es.po
odoo/addons/contract_price_revision/i18n/fr.po
odoo/addons/contract_price_revision/i18n/it.po
odoo/addons/contract_price_revision/models/__init__.py
odoo/addons/contract_price_revision/models/contract_line.py
odoo/addons/contract_price_revision/readme/CONTRIBUTORS.md
odoo/addons/contract_price_revision/readme/DESCRIPTION.md
odoo/addons/contract_price_revision/readme/USAGE.md
odoo/addons/contract_price_revision/security/ir.model.access.csv
odoo/addons/contract_price_revision/static/description/icon.png
odoo/addons/contract_price_revision/static/description/index.html
odoo/addons/contract_price_revision/tests/__init__.py
odoo/addons/contract_price_revision/tests/test_contract_price_revision.py
odoo/addons/contract_price_revision/views/contract_line.xml
odoo/addons/contract_price_revision/wizards/__init__.py
odoo/addons/contract_price_revision/wizards/contract_price_revision.py
odoo/addons/contract_price_revision/wizards/contract_price_revision_views.xml
odoo_addon_contract_price_revision-18.0.1.0.0.4.dist-info/METADATA
odoo_addon_contract_price_revision-18.0.1.0.0.4.dist-info/WHEEL
odoo_addon_contract_price_revision-18.0.1.0.0.4.dist-info/top_level.txt
odoo_addon_contract_price_revision-18.0.1.0.0.4.dist-info/RECORD
